teeheesmart/__init__.py
teeheesmart/constants.py
teeheesmart/media_switch.py
teeheesmart/url_parser.py
teeheesmart/hex/__init__.py
teeheesmart/hex/io.py
teeheesmart/hex/media_switch.py
teeheesmart-0.9.0.dist-info/METADATA
teeheesmart-0.9.0.dist-info/WHEEL
teeheesmart-0.9.0.dist-info/licenses/LICENSE
teeheesmart-0.9.0.dist-info/RECORD
