Metadata-Version: 2.4
Name: teeheesmart
Version: 0.9.0
Summary: API for controlling a TESmart media switch using Hex protocol
Project-URL: Homepage, https://github.com/krohrbaugh/teeheesmart
Project-URL: Bug Tracker, https://github.com/krohrbaugh/teeheesmart/issues
Author-email: Kevin Rohrbaugh <code@rhrbgh.com>
License-File: LICENSE
Keywords: hdmi,home assistant,home automation,tesmart,video
Classifier: Development Status :: 4 - Beta
Classifier: Intended Audience :: Developers
Classifier: License :: OSI Approved :: MIT License
Classifier: Natural Language :: English
Classifier: Operating System :: OS Independent
Classifier: Programming Language :: Python :: 3
Classifier: Topic :: Home Automation
Classifier: Topic :: Multimedia :: Video
Classifier: Topic :: Software Development :: Libraries :: Python Modules
Requires-Python: >=3.12
